IOHMM/IOHMM.py
IOHMM/__init__.py
IOHMM/forward_backward.py
IOHMM/linear_models.py
IOHMM-0.0.3.dist-info/LICENCE
IOHMM-0.0.3.dist-info/METADATA
IOHMM-0.0.3.dist-info/WHEEL
IOHMM-0.0.3.dist-info/top_level.txt
IOHMM-0.0.3.dist-info/zip-safe
IOHMM-0.0.3.dist-info/RECORD
