Metadata-Version: 2.1
Name: IOHMM
Version: 0.0.3
Summary: A python library for Input Output Hidden Markov Models
Home-page: https://github.com/Mogeng/IOHMM
Author: Mogeng Yin
Author-email: mogengyin@berkeley.edu
License: BSD License
Keywords: python hidden-markov-model graphical-models sequence-to-sequence machine-learning linear-models sequence-labeling supervised-learning semi-supervised-learning unsupervised-learning time-series scikit-learn statsmodels
Platform: UNKNOWN
Classifier: Development Status :: 2 - Pre-Alpha
Classifier: Environment :: Console
Classifier: Intended Audience :: Science/Research
Classifier: Intended Audience :: End Users/Desktop
Classifier: Intended Audience :: Developers
Classifier: Topic :: Scientific/Engineering
Classifier: License :: OSI Approved :: BSD License
Classifier: Programming Language :: Python :: 3.7
Classifier: Programming Language :: Python :: 3.8
Classifier: Programming Language :: Python :: 3.9
Requires-Dist: numpy (>=1.20.0)
Requires-Dist: future (>=0.18.2)
Requires-Dist: pandas (>=1.2.1)
Requires-Dist: scikit-learn (>=0.24.1)
Requires-Dist: scipy (>=1.6.0)
Requires-Dist: statsmodels (>=0.12.2)
Provides-Extra: tests
Requires-Dist: flake8 (>=3.8.4) ; extra == 'tests'
Requires-Dist: mock (>=3.9.1) ; extra == 'tests'
Requires-Dist: nose (>=1.3.7) ; extra == 'tests'
Requires-Dist: coveralls (>=3.0.0) ; extra == 'tests'
Requires-Dist: pytest ; extra == 'tests'
